airflow_ha/__init__.py
airflow_ha/common.py
airflow_ha/operator.py
airflow_ha/task.py
airflow_ha/tests/conftest.py
airflow_ha/tests/test_config.py
airflow_ha/tests/test_operator.py
airflow_ha/tests/config/config.yaml
airflow_ha-1.6.2.dist-info/METADATA
airflow_ha-1.6.2.dist-info/WHEEL
airflow_ha-1.6.2.dist-info/licenses/LICENSE
airflow_ha-1.6.2.dist-info/RECORD
